onbbu/__init__.py
onbbu/__init__.pyi
onbbu/database.py
onbbu/database.pyi
onbbu/emitter.py
onbbu/emitter.pyi
onbbu/etcd.py
onbbu/etcd.pyi
onbbu/http.py
onbbu/http.pyi
onbbu/logger.py
onbbu/logger.pyi
onbbu/manager.py
onbbu/manager.pyi
onbbu/paginate.py
onbbu/paginate.pyi
onbbu/template.py
onbbu/template.pyi
onbbu-0.2.3.dist-info/licenses/LICENSE
onbbu-0.2.3.dist-info/METADATA
onbbu-0.2.3.dist-info/WHEEL
onbbu-0.2.3.dist-info/entry_points.txt
onbbu-0.2.3.dist-info/top_level.txt
onbbu-0.2.3.dist-info/RECORD
