Metadata-Version: 2.4
Name: onbbu
Version: 0.2.3
Summary: Onbbu 🛠️🐍 – Hexagonal Architecture for Python
Author-email: Javier Avila <njavilas2015@gmail.com>
License-Expression: MIT
Project-URL: Homepage, https://github.com/njavilas2015/onbbu
Project-URL: Bug Tracker, https://github.com/njavilas2015/onbbu/issues
Classifier: Programming Language :: Python :: 3
Classifier: Operating System :: OS Independent
License-File: LICENSE
Requires-Dist: pydantic>=2.10.6
Requires-Dist: pytest>=8.3.4
Requires-Dist: asyncpg>=0.30.0
Requires-Dist: aerich>=0.8.2
Requires-Dist: rich>=13.9.4
Requires-Dist: tortoise-orm>=0.24.1
Requires-Dist: aiosqlite>=0.21.0
Requires-Dist: typing-extensions>=4.13.1
Requires-Dist: starlette>=0.46.0
Requires-Dist: uvicorn>=0.34.0
Requires-Dist: black>=25.1.0
Requires-Dist: colorama>=0.4.6
Requires-Dist: build>=1.2.2
Requires-Dist: twine>=6.1.0
Requires-Dist: mypy>=1.15.0
Requires-Dist: etcd3>=0.12.0
Requires-Dist: Jinja2>=3.1.6
Dynamic: license-file
